pynewdisk/__init__.py
PyNewDisk-0.0.1.dist-info/LICENSE
PyNewDisk-0.0.1.dist-info/METADATA
PyNewDisk-0.0.1.dist-info/WHEEL
PyNewDisk-0.0.1.dist-info/top_level.txt
PyNewDisk-0.0.1.dist-info/RECORD
